tlid/__init__.py
tlid/tlidcli.py
tlid-0.1.17.dist-info/METADATA
tlid-0.1.17.dist-info/WHEEL
tlid-0.1.17.dist-info/entry_points.txt
tlid-0.1.17.dist-info/top_level.txt
tlid-0.1.17.dist-info/RECORD
