Metadata-Version: 2.1
Name: tlid
Version: 0.1.17
Summary: A utility for creating datetime-based strings for file naming in timeline.
Home-page: https://github.com/tlid/tlid/tree/master/src/python
Author: GUillaume Isabelle
Author-email: jgi@jgwill.com
Classifier: Programming Language :: Python :: 2
Classifier: License :: OSI Approved :: MIT License
Classifier: Operating System :: OS Independent
Requires-Python: >=2.7
